dirio/__init__.py
dirio-0.1.4.dist-info/LICENSE
dirio-0.1.4.dist-info/METADATA
dirio-0.1.4.dist-info/WHEEL
dirio-0.1.4.dist-info/top_level.txt
dirio-0.1.4.dist-info/zip-safe
dirio-0.1.4.dist-info/RECORD
