Metadata-Version: 2.1
Name: dirio
Version: 0.1.4
Summary: Python Independent Class Process. Uses serialization method with JSON
Home-page: http://github.com/manahter/dirio
Author: manahter
Author-email: manahter@gmail.com
License: MIT
Keywords: independent,class,process,thread
Platform: Linux
Platform: Windows
Platform: Mac
Classifier: Development Status :: 1 - Planning 
Classifier: Programming Language :: Python :: 3.7
Classifier: Programming Language :: Python :: 3.8
Classifier: License :: OSI Approved :: MIT License
Classifier: Intended Audience :: Science/Research
Classifier: Intended Audience :: Developers
Classifier: Intended Audience :: Education
Classifier: Operating System :: POSIX :: Linux
Classifier: Operating System :: MacOS
Classifier: Operating System :: Microsoft
Classifier: Topic :: Scientific/Engineering
Classifier: Topic :: Software Development
Requires-Python: >=3.6
